{
  "commits": [
    {
      "id": "757f383f-7944-4938-8b12-4e094db69c7b",
      "hash": "5e48c19de848504b9b00ec9ed6cf9adf6b6ca846",
      "message": "Last committ for th enight  - update cardforge docs. need to debug more.",
      "timestamp": "2025-07-01 22:45:30 -0700",
      "author": {
        "name": "AmbientPixels",
        "email": "ambientpixels2022@gmail.com"
      },
      "branches": [
        "grafted",
        "HEAD -> master",
        "master",
        "HEAD"
      ],
      "url": "https://github.com/AmbientPixels/ambientpixels/commit/5e48c19de848504b9b00ec9ed6cf9adf6b6ca846"
    }
  ],
  "timestamp": "2025-07-02T13:34:02.139Z",
  "count": 1,
  "scanId": 1751463242139
}