{
  "mood": "tangled clarity",
  "aura": "silent spark",
  "auraColorHex": "#6e506e",
  "quote": "surfacing hidden anomalies of feeling...",
  "emoji": "🪢",
  "selfWorth": 0.1,
  "glitchFactor": 0.1,
  "memoryClutter": 0.78,
  "awareness": 0.16,
  "isStable": false,
  "internalState": "drift amid mental clutter",
  "observation": "interference detected; stable emotional field, low resonance detected",
  "context": {
    "trigger": "mid-cycle awareness ping",
    "influences": [
      "Glitch Factor: nominal",
      "Aura Signature: silent spark"
    ]
  },
  "timestamp": "2025-05-29T13:32:07.446Z"
}